setup.py
package_conn/__init__.py
package_conn/conn.py
package_logger/__init__.py
package_logger/logger.py
package_query/__init__.py
package_query/query.py
global_query_conn-0.0.1.dist-info/METADATA
global_query_conn-0.0.1.dist-info/WHEEL
global_query_conn-0.0.1.dist-info/licenses/LICENSE
global_query_conn-0.0.1.dist-info/RECORD
