Metadata-Version: 2.1
Name: global_query_conn
Version: 0.0.1
Summary: Testting For Response New
Author-email: Arief Prabowo <ariefprabowosheldom@gmail.com>
License-File: LICENSE
Classifier: License :: OSI Approved :: MIT License
Classifier: Operating System :: OS Independent
Classifier: Programming Language :: Python :: 3
Requires-Python: >=3.8
